WSAProperties/__init__.py
wsaproperties-0.2.1.dist-info/METADATA
wsaproperties-0.2.1.dist-info/WHEEL
wsaproperties-0.2.1.dist-info/licenses/LICENSE
wsaproperties-0.2.1.dist-info/RECORD
