Metadata-Version: 2.3
Name: WSAProperties
Version: 0.2.1
Summary: Package for calculating the properties of water/steam/air
Project-URL: Issues, https://t.me/cubebug
Author-email: Mikhael <shofer2007@gmail.com>, Lev <ooooooorrrrr@gmail.com>
License-File: LICENSE
Classifier: License :: OSI Approved :: MIT License
Classifier: Operating System :: OS Independent
Classifier: Programming Language :: Python :: 3
Requires-Python: >=3.8
